Part3/control_unit.v
module control_unit(OPCODE, IMM, SIGN, WRITEENABLE, ALUOP);
    input[7:0] OPCODE;
    output reg IMM, SIGN;
    output reg WRITEENABLE;
    output reg [2:0] ALUOP;


    // ...existing code...
    always @(OPCODE) begin
        // Default values
        #1
        case (OPCODE)
            8'b0000_0000: begin // LOADI            READREG2
                IMM = 1'b1;
                SIGN = 1'b0;
                WRITEENABLE = 1'b1;
                ALUOP = 3'b000; // ADD (for immediate)
            end
            8'b0000_0001: begin // MOV              READREG2
                IMM = 1'b0;
                SIGN = 1'b0;
                WRITEENABLE = 1'b1;
                ALUOP = 3'b000; // ADD (pass-through)
            end
            8'b0000_0010: begin // ADD              READREG2, READREG1
                IMM = 1'b0;
                SIGN = 1'b0;
                WRITEENABLE = 1'b1;
                ALUOP = 3'b001; // ADD
            end
            8'b0000_0011: begin // SUB              READREG1, READREG2
                IMM = 1'b0;
                SIGN = 1'b1;
                WRITEENABLE = 1'b1;
                ALUOP = 3'b001; // SUB
            end
            8'b0000_0100: begin // AND              READREG1, READREG2
                IMM = 1'b0;
                SIGN = 1'b0;
                WRITEENABLE = 1'b1;
                ALUOP = 3'b010; // AND
            end
            8'b0000_0101: begin // OR               READREG1, READREG2
                IMM = 1'b0;
                SIGN = 1'b0;
                WRITEENABLE = 1'b1;
                ALUOP = 3'b011; // OR
            end
        endcase
    end  

endmodule

Part3/alu.v
/*
Group 43
Thisen Lakdinu, Shashika sathsarani
Microprocessor implementation part-1 test case.
Date:-20/05/2025
*/


// DATA1 and DATA2 are the inputs
// module for function add and sub
module addunit (DATA1, DATA2, RESULT);
    input[7:0] DATA1, DATA2;
    output[7:0] RESULT;
    
    assign #2 RESULT =  DATA1 + DATA2;
endmodule

//module for function forwarad
module forward (DATA2, RESULT);
    input[7:0] DATA2;
    output[7:0] RESULT;

    assign  #1 RESULT = DATA2;
endmodule

//module for function and
module andunit (DATA1, DATA2, RESULT);
    input[7:0] DATA1, DATA2;
    output[7:0] RESULT;

    assign #1 RESULT = DATA1 & DATA2;
endmodule

//module for function or
module orunit (DATA1, DATA2, RESULT);
    input[7:0] DATA1, DATA2;
    output[7:0] RESULT;

    assign #1 RESULT = DATA1 | DATA2;
endmodule

//module for alu unit
module alu (DATA1, DATA2, RESULT, SELECT);
    input[7:0] DATA1, DATA2;
    input[2:0] SELECT;
    output reg[7:0] RESULT;
    wire [7:0] forward_out, add_out, and_out, or_out;

    forward fwd (.DATA2(DATA2), .RESULT(forward_out));               //instance for forkward
    addunit add (.DATA1(DATA1), .DATA2(DATA2), .RESULT(add_out));    //instance for add
    andunit andg (.DATA1(DATA1), .DATA2(DATA2), .RESULT(and_out));   //instance for and
    orunit org (.DATA1(DATA1), .DATA2(DATA2), .RESULT(or_out));      //instance for or


    //multiplexer for selector input
    always @(forward_out or add_out or and_out or or_out or SELECT) 
    begin
        if (SELECT == 3'b000)           //forward
            //forward fwd (.DATA2(DATA2), .RESULT(RESULT));
            RESULT = forward_out;
        else if (SELECT == 3'b001)     //add
            RESULT = add_out;
        else if (SELECT == 3'b010)     //and
            RESULT = and_out;
        else if (SELECT == 3'b011)     //or
            RESULT = or_out;
    end
endmodule

Part3/mux.v
module mux(DATA1, DATA2, SELECT, OUTPUT);
    input [7:0] DATA1, DATA2;
    input SELECT;
    output reg [7:0] OUTPUT;

    always @(DATA1,DATA2,SELECT) 
    begin
        if (SELECT == 1'b1)
            OUTPUT = DATA1;
        else
            OUTPUT = DATA2;
    end
endmodule

Part3/two_s_comple.v
//module for the 2's complement
//return the negative value of the input
module two_s_comple(DATA2, OUTPUT);
    input [7:0] DATA2;
    output [7:0] OUTPUT;

    assign #1 OUTPUT = ~DATA2 + 1;
endmodule

Part2/reg_file.v
/*
Group 43
Thisen Lakdinu, Shashika Sathsarani
Microprocessor implementation part-2.
Date:-20/05/2025
*/

module reg_file (
    IN, OUT1, OUT2, 
    INADDRESS, OUT1ADDRESS, OUT2ADDRESS, 
    WRITE, CLK, RESET
);

    // Port Declarations
    input [2:0] OUT2ADDRESS, OUT1ADDRESS, INADDRESS;  // 3-bit addresses for 8 registers (0 to 7)
    input [7:0] IN;                                   // 8-bit data input
    input WRITE, CLK, RESET;                          // Control signals: Write Enable, Clock, and Reset

    output [7:0] OUT1, OUT2;                          // 8-bit data outputs

    // Register bank: 8 registers, each 8 bits wide
    reg [7:0] REGISTER[7:0];

    // Output assignments with delay of 2 time units
    assign #2 OUT1 = REGISTER[OUT1ADDRESS];  // Reads content of register specified by OUT1ADDRESS
    assign #2 OUT2 = REGISTER[OUT2ADDRESS];  // Reads content of register specified by OUT2ADDRESS

    // Always block triggered at the positive edge of the clock
    always @ (posedge CLK)
    begin
        if (RESET == 1'b1) // When RESET is high, clear all registers
        begin
            #1 REGISTER[0] = 8'b00000000;
               REGISTER[1] = 8'b00000000;
               REGISTER[2] = 8'b00000000;
               REGISTER[3] = 8'b00000000;
               REGISTER[4] = 8'b00000000;
               REGISTER[5] = 8'b00000000;
               REGISTER[6] = 8'b00000000;
               REGISTER[7] = 8'b00000000;
            // Note: A loop could be used here, but manually writing ensures deterministic behavior
        end
        else if (WRITE == 1'b1) // If WRITE is enabled, write data to specified register
        begin
            #1 REGISTER[INADDRESS] = IN;
        end
    end

    // Initial block to monitor and print the register values during simulation
    initial 
    begin
        $monitor("Time:-%0d\nReg1:-%8d\nReg2:-%8d\nReg3:-%8d\nReg4:-%8d\nReg5:-%8d\nReg6:-%8d\nReg7:-%8d\nReg8:-%8d\n", 
            $time, 
            REGISTER[0], REGISTER[1], REGISTER[2], REGISTER[3], 
            REGISTER[4], REGISTER[5], REGISTER[6], REGISTER[7]);
    end   

endmodule

Part3/cpu.v
`include "reg_file.v"
`include "control_unit.v"
`include "mux.v"
`include "alu.v"
`include "two_s_comple.v"

module cpu(INSTRUCTION, RESET, CLK, PC);
    input RESET, CLK;
    input [31:0] INSTRUCTION;
    output reg [31:0] PC;

    // Internal signals
    wire [2:0] READREG1, READREG2, WRITEREG, ALUOP;
    wire [7:0] IMMEDIATE, REGOUT1, REGOUT2, IN2_S, OUT2_S, OUT_SIGN, OUT_IMM, ALURESULT;
    wire WRITEENABLE, IMM, SIGN;
    wire [7:0] OPCODE;
    reg [31:0] PCreg;

    // Instruction decoding
    assign OPCODE = INSTRUCTION[31:24];
    assign READREG1 = INSTRUCTION[15:8];
    assign WRITEREG = INSTRUCTION[23:16];
    assign READREG2 = INSTRUCTION[7:0];
    assign IMMEDIATE = INSTRUCTION[7:0];

    // Module instantiations
    reg_file reg_file_inst (
        .IN(ALURESULT),
        .OUT1(REGOUT1),
        .OUT2(REGOUT2),
        .INADDRESS(WRITEREG),
        .OUT1ADDRESS(READREG1),
        .OUT2ADDRESS(READREG2),
        .WRITE(WRITEENABLE),
        .CLK(CLK),
        .RESET(RESET)
    );

    mux mux1 (
        .DATA1(OUT2_S),
        .DATA2(REGOUT2),
        .SELECT(SIGN),
        .OUTPUT(OUT_SIGN)
    );

    two_s_comple twos_inst (
        .DATA2(REGOUT2),
        .OUTPUT(OUT2_S)
    );

    mux mux2 (
        .DATA1(IMMEDIATE),
        .DATA2(OUT_SIGN),
        .SELECT(IMM),
        .OUTPUT(OUT_IMM)
    );

    alu alu_inst (
        .DATA1(REGOUT1),
        .DATA2(OUT_IMM),
        .RESULT(ALURESULT),
        .SELECT(ALUOP)
    );

    control_unit control_inst (
        .OPCODE(OPCODE),
        .IMM(IMM),
        .SIGN(SIGN),
        .WRITEENABLE(WRITEENABLE),
        .ALUOP(ALUOP)
    );

    // PC update logic
    always @(posedge CLK) 
    begin
        if (RESET == 1'b1) 
            begin
                #1
                PC = 0;
                PCreg = 0;
            end
        else #1 PC = PCreg;
    end

    always @(PC) 
    begin
        #1 PCreg = PCreg + 4;
    end
endmodule

Part3/cpu_tb.v
// Computer Architecture (CO224) - Lab 05
// Design: Testbench of Integrated CPU of Simple Processor
// Author: Isuru Nawinne

`include "cpu.v"

module cpu_tb;

    reg CLK, RESET;
    wire [31:0] PC;
    wire [31:0] INSTRUCTION;
    
    /* 
    ------------------------
     SIMPLE INSTRUCTION MEM
    ------------------------
    */
    
    // TODO: Initialize an array of registers (8x1024) named 'instr_mem' to be used as instruction memory
    reg [7:0] instr_mem [1023:0];
    
    // TODO: Create combinational logic to support CPU instruction fetching, given the Program Counter(PC) value 
    assign #2 INSTRUCTION = {instr_mem[PC+3], instr_mem[PC+2], instr_mem[PC+1], instr_mem[PC]};
    //       (make sure you include the delay for instruction fetching here)
    
    initial
    begin
        // Initialize instruction memory with the set of instructions you need execute on CPU
        
        // METHOD 1: manually loading instructions to instr_mem
        //{instr_mem[10'd3], instr_mem[10'd2], instr_mem[10'd1], instr_mem[10'd0]} = 32'b00000000000001000000000000000101;
        //{instr_mem[10'd7], instr_mem[10'd6], instr_mem[10'd5], instr_mem[10'd4]} = 32'b00000000000000100000000000001001;
        //{instr_mem[10'd11], instr_mem[10'd10], instr_mem[10'd9], instr_mem[10'd8]} = 32'b00000010000001100000010000000010;
        
        // METHOD 2: loading instr_mem content from instr_mem.mem file
        $readmemb("instr_mem.mem", instr_mem);
    end
    
    /* 
    -----
     CPU
    -----
    */
    cpu mycpu(INSTRUCTION, RESET, CLK, PC);

    initial
    begin
    
        // generate files needed to plot the waveform using GTKWave
        $dumpfile("cpu_wavedata.vcd");
		$dumpvars(0, cpu_tb);
        
        CLK = 1'b0;
        RESET = 1'b0;
        
        // TODO: Reset the CPU (by giving a pulse to RESET signal) to start the program execution
        RESET = 1'b1;
        #5;
        RESET = 1'b0;
        
        // finish simulation after some time
        #500
        $finish;
        
    end
    
    // clock signal generation
    always
        #4 CLK = ~CLK;
        

endmodule

Part3/cpu_wavedata.vcd
$date
	Sun Jun 01 05:42:48 2025
$end
$version
	Icarus Verilog
$end
$timescale
	1s
$end
$scope module cpu_tb $end
$var wire 32 ! PC [31:0] $end
$var wire 32 " INSTRUCTION [31:0] $end
$var reg 1 # CLK $end
$var reg 1 $ RESET $end
$scope module mycpu $end
$var wire 1 # CLK $end
$var wire 32 % INSTRUCTION [31:0] $end
$var wire 1 $ RESET $end
$var wire 3 & WRITEREG [2:0] $end
$var wire 1 ' WRITEENABLE $end
$var wire 1 ( SIGN $end
$var wire 8 ) REGOUT2 [7:0] $end
$var wire 8 * REGOUT1 [7:0] $end
$var wire 3 + READREG2 [2:0] $end
$var wire 3 , READREG1 [2:0] $end
$var wire 8 - OUT_SIGN [7:0] $end
$var wire 8 . OUT_IMM [7:0] $end
$var wire 8 / OUT2_S [7:0] $end
$var wire 8 0 OPCODE [7:0] $end
$var wire 8 1 IMMEDIATE [7:0] $end
$var wire 1 2 IMM $end
$var wire 8 3 ALURESULT [7:0] $end
$var wire 3 4 ALUOP [2:0] $end
$var reg 32 5 PC [31:0] $end
$var reg 32 6 PCreg [31:0] $end
$scope module alu_inst $end
$var wire 8 7 or_out [7:0] $end
$var wire 8 8 forward_out [7:0] $end
$var wire 8 9 and_out [7:0] $end
$var wire 8 : add_out [7:0] $end
$var wire 3 ; SELECT [2:0] $end
$var wire 8 < DATA2 [7:0] $end
$var wire 8 = DATA1 [7:0] $end
$var reg 8 > RESULT [7:0] $end
$scope module add $end
$var wire 8 ? RESULT [7:0] $end
$var wire 8 @ DATA2 [7:0] $end
$var wire 8 A DATA1 [7:0] $end
$upscope $end
$scope module andg $end
$var wire 8 B RESULT [7:0] $end
$var wire 8 C DATA2 [7:0] $end
$var wire 8 D DATA1 [7:0] $end
$upscope $end
$scope module fwd $end
$var wire 8 E RESULT [7:0] $end
$var wire 8 F DATA2 [7:0] $end
$upscope $end
$scope module org $end
$var wire 8 G RESULT [7:0] $end
$var wire 8 H DATA2 [7:0] $end
$var wire 8 I DATA1 [7:0] $end
$upscope $end
$upscope $end
$scope module control_inst $end
$var wire 8 J OPCODE [7:0] $end
$var reg 3 K ALUOP [2:0] $end
$var reg 1 2 IMM $end
$var reg 1 ( SIGN $end
$var reg 1 ' WRITEENABLE $end
$upscope $end
$scope module mux1 $end
$var wire 1 ( SELECT $end
$var wire 8 L DATA2 [7:0] $end
$var wire 8 M DATA1 [7:0] $end
$var reg 8 N OUTPUT [7:0] $end
$upscope $end
$scope module mux2 $end
$var wire 8 O DATA1 [7:0] $end
$var wire 8 P DATA2 [7:0] $end
$var wire 1 2 SELECT $end
$var reg 8 Q OUTPUT [7:0] $end
$upscope $end
$scope module reg_file_inst $end
$var wire 1 # CLK $end
$var wire 8 R IN [7:0] $end
$var wire 3 S INADDRESS [2:0] $end
$var wire 8 T OUT1 [7:0] $end
$var wire 3 U OUT1ADDRESS [2:0] $end
$var wire 8 V OUT2 [7:0] $end
$var wire 3 W OUT2ADDRESS [2:0] $end
$var wire 1 $ RESET $end
$var wire 1 ' WRITE $end
$upscope $end
$scope module twos_inst $end
$var wire 8 X DATA2 [7:0] $end
$var wire 8 Y OUTPUT [7:0] $end
$upscope $end
$upscope $end
$upscope $end
$enddefinitions $end
$comment Show the parameter values. $end
$dumpall
$end
#0
$dumpvars
bx Y
bx X
bx W
bx V
bx U
bx T
bx S
bx R
bx Q
bx P
bx O
bx N
bx M
bx L
bx K
bx J
bx I
bx H
bx G
bx F
bx E
bx D
bx C
bx B
bx A
bx @
bx ?
bx >
bx =
bx <
bx ;
bx :
bx 9
bx 8
bx 7
bx 6
bx 5
bx 4
bx 3
x2
bx 1
bx 0
bx /
bx .
bx -
bx ,
bx +
bx *
bx )
x(
x'
bx &
bx %
1$
0#
bx "
bx !
$end
#4
1#
#5
b0 6
b0 !
b0 5
0$
#6
b100 6
#7
b0 ,
b0 U
b100 &
b100 S
b101 +
b101 W
b0 0
b0 J
b101 1
b101 O
b1000000000000000101 "
b1000000000000000101 %
#8
b101 .
b101 <
b101 @
b101 C
b101 F
b101 H
b101 Q
b0 4
b0 ;
b0 K
1'
0(
12
0#
#9
b101 3
b101 >
b101 R
b0 -
b0 N
b0 P
bx1x1 7
bx1x1 G
b0x0x 9
b0x0x B
b101 8
b101 E
b0 *
b0 =
b0 A
b0 D
b0 I
b0 T
b0 )
b0 L
b0 V
b0 X
#10
b101 7
b101 G
b0 9
b0 B
b0 /
b0 M
b0 Y
#11
b101 :
b101 ?
#12
1#
#13
b100 !
b100 5
#14
b1000 6
#15
b10 &
b10 S
b1 +
b1 W
b1001 .
b1001 <
b1001 @
b1001 C
b1001 F
b1001 H
b1001 Q
b1001 1
b1001 O
b100000000000001001 "
b100000000000001001 %
#16
b1001 3
b1001 >
b1001 R
b1001 7
b1001 G
b1001 8
b1001 E
0#
#17
b1001 :
b1001 ?
#20
1#
#21
b1000 !
b1000 5
#22
b1100 6
#23
b100 ,
b100 U
b110 &
b110 S
b10 +
b10 W
b10 .
b10 <
b10 @
b10 C
b10 F
b10 H
b10 Q
b10 0
b10 J
b10 1
b10 O
b10000001100000010000000010 "
b10000001100000010000000010 %
#24
b0 .
b0 <
b0 @
b0 C
b0 F
b0 H
b0 Q
b10 7
b10 G
b1 4
b1 ;
b1 K
02
b10 8
b10 E
0#
#25
b1001 .
b1001 <
b1001 @
b1001 C
b1001 F
b1001 H
b1001 Q
b1001 -
b1001 N
b1001 P
b0 7
b0 G
b0 8
b0 E
b101 *
b101 =
b101 A
b101 D
b101 I
b101 T
b1001 )
b1001 L
b1001 V
b1001 X
#26
b1 9
b1 B
b1001 8
b1001 E
b1101 7
b1101 G
b11110111 /
b11110111 M
b11110111 Y
#27
b1110 3
b1110 >
b1110 R
b1110 :
b1110 ?
#28
1#
#29
b1100 !
b1100 5
#30
b10000 6
#31
b0 ,
b0 U
b0 &
b0 S
b110 +
b110 W
b1 0
b1 J
b110 1
b110 O
b1000000000000000000000110 "
b1000000000000000000000110 %
#32
b1001 3
b1001 >
b1001 R
b0 4
b0 ;
b0 K
0#
#33
b1110 .
b1110 <
b1110 @
b1110 C
b1110 F
b1110 H
b1110 Q
b1110 -
b1110 N
b1110 P
b0 *
b0 =
b0 A
b0 D
b0 I
b0 T
b1110 )
b1110 L
b1110 V
b1110 X
#34
b1110 3
b1110 >
b1110 R
b1110 8
b1110 E
b1110 7
b1110 G
b0 9
b0 B
b11110010 /
b11110010 M
b11110010 Y
#36
1#
#37
b10000 !
b10000 5
#38
b10100 6
#39
b1 &
b1 S
b1 +
b1 W
b0 0
b0 J
b1 1
b1 O
b1110 *
b1110 =
b1110 A
b1110 D
b1110 I
b1110 T
b10000000000000001 "
b10000000000000001 %
#40
b1 .
b1 <
b1 @
b1 C
b1 F
b1 H
b1 Q
12
b1110 9
b1110 B
0#
#41
b1 3
b1 >
b1 R
b0 -
b0 N
b0 P
b1111 7
b1111 G
b0 9
b0 B
b1 8
b1 E
b0 )
b0 L
b0 V
b0 X
#42
b0 /
b0 M
b0 Y
b1111 :
b1111 ?
#44
1#
#45
b10100 !
b10100 5
#46
b11000 6
#47
b10 ,
b10 U
b10 &
b10 S
b10 0
b10 J
b1 -
b1 N
b1 P
b10000000100000001000000001 "
b10000000100000001000000001 %
b1 )
b1 L
b1 V
b1 X
#48
b1111 3
b1111 >
b1111 R
b1 4
b1 ;
b1 K
02
b11111111 /
b11111111 M
b11111111 Y
0#
#49
b1001 *
b1001 =
b1001 A
b1001 D
b1001 I
b1001 T
#50
b1001 7
b1001 G
b1 9
b1 B
#51
b1010 3
b1010 >
b1010 R
b1010 :
b1010 ?
#52
1#
#53
b11000 !
b11000 5
#54
b11100 6
#55
bx ,
bx U
bx &
bx S
bx +
bx W
bx 0
bx J
bx 1
bx O
b1010 *
b1010 =
b1010 A
b1010 D
b1010 I
b1010 T
bx "
bx %
#56
b1011 7
b1011 G
b0 9
b0 B
0#
#57
bx .
bx <
bx @
bx C
bx F
bx H
bx Q
bx -
bx N
bx P
b1011 3
b1011 >
b1011 R
bx *
bx =
bx A
bx D
bx I
bx T
bx )
bx L
bx V
bx X
b1011 :
b1011 ?
#58
bx 8
bx E
bx 7
bx G
bx 9
bx B
bx /
bx M
bx Y
#59
bx 3
bx >
bx R
bx :
bx ?
#60
1#
#61
b11100 !
b11100 5
#62
b100000 6
#64
0#
#68
1#
#69
b100000 !
b100000 5
#70
b100100 6
#72
0#
#76
1#
#77
b100100 !
b100100 5
#78
b101000 6
#80
0#
#84
1#
#85
b101000 !
b101000 5
#86
b101100 6
#88
0#
#92
1#
#93
b101100 !
b101100 5
#94
b110000 6
#96
0#
#100
1#
#101
b110000 !
b110000 5
#102
b110100 6
#104
0#
#108
1#
#109
b110100 !
b110100 5
#110
b111000 6
#112
0#
#116
1#
#117
b111000 !
b111000 5
#118
b111100 6
#120
0#
#124
1#
#125
b111100 !
b111100 5
#126
b1000000 6
#128
0#
#132
1#
#133
b1000000 !
b1000000 5
#134
b1000100 6
#136
0#
#140
1#
#141
b1000100 !
b1000100 5
#142
b1001000 6
#144
0#
#148
1#
#149
b1001000 !
b1001000 5
#150
b1001100 6
#152
0#
#156
1#
#157
b1001100 !
b1001100 5
#158
b1010000 6
#160
0#
#164
1#
#165
b1010000 !
b1010000 5
#166
b1010100 6
#168
0#
#172
1#
#173
b1010100 !
b1010100 5
#174
b1011000 6
#176
0#
#180
1#
#181
b1011000 !
b1011000 5
#182
b1011100 6
#184
0#
#188
1#
#189
b1011100 !
b1011100 5
#190
b1100000 6
#192
0#
#196
1#
#197
b1100000 !
b1100000 5
#198
b1100100 6
#200
0#
#204
1#
#205
b1100100 !
b1100100 5
#206
b1101000 6
#208
0#
#212
1#
#213
b1101000 !
b1101000 5
#214
b1101100 6
#216
0#
#220
1#
#221
b1101100 !
b1101100 5
#222
b1110000 6
#224
0#
#228
1#
#229
b1110000 !
b1110000 5
#230
b1110100 6
#232
0#
#236
1#
#237
b1110100 !
b1110100 5
#238
b1111000 6
#240
0#
#244
1#
#245
b1111000 !
b1111000 5
#246
b1111100 6
#248
0#
#252
1#
#253
b1111100 !
b1111100 5
#254
b10000000 6
#256
0#
#260
1#
#261
b10000000 !
b10000000 5
#262
b10000100 6
#264
0#
#268
1#
#269
b10000100 !
b10000100 5
#270
b10001000 6
#272
0#
#276
1#
#277
b10001000 !
b10001000 5
#278
b10001100 6
#280
0#
#284
1#
#285
b10001100 !
b10001100 5
#286
b10010000 6
#288
0#
#292
1#
#293
b10010000 !
b10010000 5
#294
b10010100 6
#296
0#
#300
1#
#301
b10010100 !
b10010100 5
#302
b10011000 6
#304
0#
#308
1#
#309
b10011000 !
b10011000 5
#310
b10011100 6
#312
0#
#316
1#
#317
b10011100 !
b10011100 5
#318
b10100000 6
#320
0#
#324
1#
#325
b10100000 !
b10100000 5
#326
b10100100 6
#328
0#
#332
1#
#333
b10100100 !
b10100100 5
#334
b10101000 6
#336
0#
#340
1#
#341
b10101000 !
b10101000 5
#342
b10101100 6
#344
0#
#348
1#
#349
b10101100 !
b10101100 5
#350
b10110000 6
#352
0#
#356
1#
#357
b10110000 !
b10110000 5
#358
b10110100 6
#360
0#
#364
1#
#365
b10110100 !
b10110100 5
#366
b10111000 6
#368
0#
#372
1#
#373
b10111000 !
b10111000 5
#374
b10111100 6
#376
0#
#380
1#
#381
b10111100 !
b10111100 5
#382
b11000000 6
#384
0#
#388
1#
#389
b11000000 !
b11000000 5
#390
b11000100 6
#392
0#
#396
1#
#397
b11000100 !
b11000100 5
#398
b11001000 6
#400
0#
#404
1#
#405
b11001000 !
b11001000 5
#406
b11001100 6
#408
0#
#412
1#
#413
b11001100 !
b11001100 5
#414
b11010000 6
#416
0#
#420
1#
#421
b11010000 !
b11010000 5
#422
b11010100 6
#424
0#
#428
1#
#429
b11010100 !
b11010100 5
#430
b11011000 6
#432
0#
#436
1#
#437
b11011000 !
b11011000 5
#438
b11011100 6
#440
0#
#444
1#
#445
b11011100 !
b11011100 5
#446
b11100000 6
#448
0#
#452
1#
#453
b11100000 !
b11100000 5
#454
b11100100 6
#456
0#
#460
1#
#461
b11100100 !
b11100100 5
#462
b11101000 6
#464
0#
#468
1#
#469
b11101000 !
b11101000 5
#470
b11101100 6
#472
0#
#476
1#
#477
b11101100 !
b11101100 5
#478
b11110000 6
#480
0#
#484
1#
#485
b11110000 !
b11110000 5
#486
b11110100 6
#488
0#
#492
1#
#493
b11110100 !
b11110100 5
#494
b11111000 6
#496
0#
#500
1#
#501
b11111000 !
b11111000 5
#502
b11111100 6
